odoo/addons/mrp_mto_with_stock_purchase/README.rst
odoo/addons/mrp_mto_with_stock_purchase/__init__.py
odoo/addons/mrp_mto_with_stock_purchase/__manifest__.py
odoo/addons/mrp_mto_with_stock_purchase/i18n/de.po
odoo/addons/mrp_mto_with_stock_purchase/i18n/mrp_mto_with_stock_purchase.pot
odoo/addons/mrp_mto_with_stock_purchase/models/__init__.py
odoo/addons/mrp_mto_with_stock_purchase/models/mrp_production.py
odoo/addons/mrp_mto_with_stock_purchase/readme/CONFIGURE.rst
odoo/addons/mrp_mto_with_stock_purchase/readme/CONTRIBUTORS.rst
odoo/addons/mrp_mto_with_stock_purchase/readme/DESCRIPTION.rst
odoo/addons/mrp_mto_with_stock_purchase/readme/USAGE.rst
odoo/addons/mrp_mto_with_stock_purchase/static/description/icon.png
odoo/addons/mrp_mto_with_stock_purchase/static/description/index.html
odoo11_addon_mrp_mto_with_stock_purchase-11.0.1.0.0.99.dev8.dist-info/METADATA
odoo11_addon_mrp_mto_with_stock_purchase-11.0.1.0.0.99.dev8.dist-info/WHEEL
odoo11_addon_mrp_mto_with_stock_purchase-11.0.1.0.0.99.dev8.dist-info/top_level.txt
odoo11_addon_mrp_mto_with_stock_purchase-11.0.1.0.0.99.dev8.dist-info/RECORD
